EX09/PWM12.sv
module PWM12(
    input  logic        clk,
    input  logic        rst_n,
    input  logic [11:0] duty,
    output logic        PWM1,
    output logic        PWM2
);

    localparam logic [11:0] NONOVERLAP = 12'h02C;

    logic [11:0] cnt;
    logic s1, r1, s2, r2;
    logic [12:0] duty_plus_no;

    assign duty_plus_no = {1'b0, duty} + {1'b0, NONOVERLAP}; //No overflow logic so we set this addition to a 13 bit vector

    always_comb begin //Comb block for out SR latch inputes
        s2 = (cnt >= NONOVERLAP);
        r2 = (cnt >= duty);

        s1 = (!duty_plus_no[12]) && (cnt >= duty_plus_no[11:0]);
        r1 = &cnt;
    end

    always_ff @(posedge clk or negedge rst_n) begin //SR flop for PWM2
        if (!rst_n)        PWM2 <= 1'b0;
        else if (r1)       PWM2 <= 1'b0;
        else if (s1)       PWM2 <= 1'b1;
    end

    always_ff @(posedge clk or negedge rst_n) begin //SR Flop for PWM1
        if (!rst_n)        PWM1 <= 1'b0;
        else if (r2)       PWM1 <= 1'b0;
        else if (s2)       PWM1 <= 1'b1;
    end

    always_ff @(posedge clk or negedge rst_n) begin //Flop for cnt incrementor.
        if (!rst_n) cnt <= 12'd0;
        else        cnt <= cnt + 12'd1;
    end

endmodule

EX09/PWM12_tb.sv
`timescale 1ns/1ps

module PWM12_tb;

  logic clk;
  logic rst_n;
  logic [11:0] duty;
  logic PWM1, PWM2;

  PWM12 iDUT (
    .clk (clk),
    .rst_n(rst_n),
    .duty(duty),
    .PWM1(PWM1),
    .PWM2(PWM2)
  );

  initial clk = 1'b0;
  always #10 clk = ~clk; // 50 MHz (20 ns period)

  initial begin
    $dumpfile("PWM12.vcd");
    $dumpvars(0, PWM12_tb);

    rst_n = 1'b0;
    duty  = 12'h000;
    repeat (5) @(posedge clk);
    rst_n = 1'b1;

    duty = 12'h080;  // small
    repeat (5000) @(posedge clk);

    duty = 12'h800;  // medium
    repeat (5000) @(posedge clk);

    duty = 12'hF00;  // large
    repeat (5000) @(posedge clk);

    $finish;
  end

endmodule

EX09/PWM12.vcd
$date
	Mon Feb 16 11:29:27 2026
$end
$version
	ModelSim Version 2020.1
$end
$timescale
	1ps
$end

$scope module PWM12_tb $end
$var reg 1 ! clk $end
$var reg 1 " rst_n $end
$var reg 12 # duty [11:0] $end
$var reg 1 $ PWM1 $end
$var reg 1 % PWM2 $end

$scope module iDUT $end
$var parameter 12 & NONOVERLAP $end
$var wire 1 ' clk $end
$var wire 1 ( rst_n $end
$var wire 1 ) duty [11] $end
$var wire 1 * duty [10] $end
$var wire 1 + duty [9] $end
$var wire 1 , duty [8] $end
$var wire 1 - duty [7] $end
$var wire 1 . duty [6] $end
$var wire 1 / duty [5] $end
$var wire 1 0 duty [4] $end
$var wire 1 1 duty [3] $end
$var wire 1 2 duty [2] $end
$var wire 1 3 duty [1] $end
$var wire 1 4 duty [0] $end
$var reg 1 5 PWM1 $end
$var reg 1 6 PWM2 $end
$var reg 12 7 cnt [11:0] $end
$var reg 1 8 s1 $end
$var reg 1 9 r1 $end
$var reg 1 : s2 $end
$var reg 1 ; r2 $end
$var reg 13 < duty_plus_no [12:0] $end
$upscope $end
$upscope $end
$enddefinitions $end
#0
$dumpvars
0!
0"
b0 #
0$
0%
05
06
b0 7
08
09
0:
1;
b101100 <
b101100 &
0'
0(
04
03
02
01
00
0/
0.
0-
0,
0+
0*
0)
$end
#10000
1!
1'
#20000
0!
0'
#30000
1!
1'
#40000
0!
0'
#50000
1!
1'
#60000
0!
0'
#70000
1!
1'
#80000
0!
0'
#90000
1!
1'
1"
b10000000 #
1(
1-
b10101100 <
0;
#100000
0!
0'
#110000
1!
1'
b1 7
#120000
0!
0'
#130000
1!
1'
b10 7
#140000
0!
0'
#150000
1!
1'
b11 7
#160000
0!
0'
#170000
1!
1'
b100 7
#180000
0!
0'
#190000
1!
1'
b101 7
#200000
0!
0'
#210000
1!
1'
b110 7
#220000
0!
0'
#230000
1!
1'
b111 7
#240000
0!
0'
#250000
1!
1'
b1000 7
#260000
0!
0'
#270000
1!
1'
b1001 7
#280000
0!
0'
#290000
1!
1'
b1010 7
#300000
0!
0'
#310000
1!
1'
b1011 7
#320000
0!
0'
#330000
1!
1'
b1100 7
#340000
0!
0'
#350000
1!
1'
b1101 7
#360000
0!
0'
#370000
1!
1'
b1110 7
#380000
0!
0'
#390000
1!
1'
b1111 7
#400000
0!
0'
#410000
1!
1'
b10000 7
#420000
0!
0'
#430000
1!
1'
b10001 7
#440000
0!
0'
#450000
1!
1'
b10010 7
#460000
0!
0'
#470000
1!
1'
b10011 7
#480000
0!
0'
#490000
1!
1'
b10100 7
#500000
0!
0'
#510000
1!
1'
b10101 7
#520000
0!
0'
#530000
1!
1'
b10110 7
#540000
0!
0'
#550000
1!
1'
b10111 7
#560000
0!
0'
#570000
1!
1'
b11000 7
#580000
0!
0'
#590000
1!
1'
b11001 7
#600000
0!
0'
#610000
1!
1'
b11010 7
#620000
0!
0'
#630000
1!
1'
b11011 7
#640000
0!
0'
#650000
1!
1'
b11100 7
#660000
0!
0'
#670000
1!
1'
b11101 7
#680000
0!
0'
#690000
1!
1'
b11110 7
#700000
0!
0'
#710000
1!
1'
b11111 7
#720000
0!
0'
#730000
1!
1'
b100000 7
#740000
0!
0'
#750000
1!
1'
b100001 7
#760000
0!
0'
#770000
1!
1'
b100010 7
#780000
0!
0'
#790000
1!
1'
b100011 7
#800000
0!
0'
#810000
1!
1'
b100100 7
#820000
0!
0'
#830000
1!
1'
b100101 7
#840000
0!
0'
#850000
1!
1'
b100110 7
#860000
0!
0'
#870000
1!
1'
b100111 7
#880000
0!
0'
#890000
1!
1'
b101000 7
#900000
0!
0'
#910000
1!
1'
b101001 7
#920000
0!
0'
#930000
1!
1'
b101010 7
#940000
0!
0'
#950000
1!
1'
b101011 7
#960000
0!
0'
#970000
1!
1'
b101100 7
1:
#980000
0!
0'
#990000
1!
1'
15
b101101 7
1$
#1000000
0!
0'
#1010000
1!
1'
b101110 7
#1020000
0!
0'
#1030000
1!
1'
b101111 7
#1040000
0!
0'
#1050000
1!
1'
b110000 7
#1060000
0!
0'
#1070000
1!
1'
b110001 7
#1080000
0!
0'
#1090000
1!
1'
b110010 7
#1100000
0!
0'
#1110000
1!
1'
b110011 7
#1120000
0!
0'
#1130000
1!
1'
b110100 7
#1140000
0!
0'
#1150000
1!
1'
b110101 7
#1160000
0!
0'
#1170000
1!
1'
b110110 7
#1180000
0!
0'
#1190000
1!
1'
b110111 7
#1200000
0!
0'
#1210000
1!
1'
b111000 7
#1220000
0!
0'
#1230000
1!
1'
b111001 7
#1240000
0!
0'
#1250000
1!
1'
b111010 7
#1260000
0!
0'
#1270000
1!
1'
b111011 7
#1280000
0!
0'
#1290000
1!
1'
b111100 7
#1300000
0!
0'
#1310000
1!
1'
b111101 7
#1320000
0!
0'
#1330000
1!
1'
b111110 7
#1340000
0!
0'
#1350000
1!
1'
b111111 7
#1360000
0!
0'
#1370000
1!
1'
b1000000 7
#1380000
0!
0'
#1390000
1!
1'
b1000001 7
#1400000
0!
0'
#1410000
1!
1'
b1000010 7
#1420000
0!
0'
#1430000
1!
1'
b1000011 7
#1440000
0!
0'
#1450000
1!
1'
b1000100 7
#1460000
0!
0'
#1470000
1!
1'
b1000101 7
#1480000
0!
0'
#1490000
1!
1'
b1000110 7
#1500000
0!
0'
#1510000
1!
1'
b1000111 7
#1520000
0!
0'
#1530000
1!
1'
b1001000 7
#1540000
0!
0'
#1550000
1!
1'
b1001001 7
#1560000
0!
0'
#1570000
1!
1'
b1001010 7
#1580000
0!
0'
#1590000
1!
1'
b1001011 7
#1600000
0!
0'
#1610000
1!
1'
b1001100 7
#1620000
0!
0'
#1630000
1!
1'
b1001101 7
#1640000
0!
0'
#1650000
1!
1'
b1001110 7
#1660000
0!
0'
#1670000
1!
1'
b1001111 7
#1680000
0!
0'
#1690000
1!
1'
b1010000 7
#1700000
0!
0'
#1710000
1!
1'
b1010001 7
#1720000
0!
0'
#1730000
1!
1'
b1010010 7
#1740000
0!
0'
#1750000
1!
1'
b1010011 7
#1760000
0!
0'
#1770000
1!
1'
b1010100 7
#1780000
0!
0'
#1790000
1!
1'
b1010101 7
#1800000
0!
0'
#1810000
1!
1'
b1010110 7
#1820000
0!
0'
#1830000
1!
1'
b1010111 7
#1840000
0!
0'
#1850000
1!
1'
b1011000 7
#1860000
0!
0'
#1870000
1!
1'
b1011001 7
#1880000
0!
0'
#1890000
1!
1'
b1011010 7
#1900000
0!
0'
#1910000
1!
1'
b1011011 7
#1920000
0!
0'
#1930000
1!
1'
b1011100 7
#1940000
0!
0'
#1950000
1!
1'
b1011101 7
#1960000
0!
0'
#1970000
1!
1'
b1011110 7
#1980000
0!
0'
#1990000
1!
1'
b1011111 7
#2000000
0!
0'
#2010000
1!
1'
b1100000 7
#2020000
0!
0'
#2030000
1!
1'
b1100001 7
#2040000
0!
0'
#2050000
1!
1'
b1100010 7
#2060000
0!
0'
#2070000
1!
1'
b1100011 7
#2080000
0!
0'
#2090000
1!
1'
b1100100 7
#2100000
0!
0'
#2110000
1!
1'
b1100101 7
#2120000
0!
0'
#2130000
1!
1'
b1100110 7
#2140000
0!
0'
#2150000
1!
1'
b1100111 7
#2160000
0!
0'
#2170000
1!
1'
b1101000 7
#2180000
0!
0'
#2190000
1!
1'
b1101001 7
#2200000
0!
0'
#2210000
1!
1'
b1101010 7
#2220000
0!
0'
#2230000
1!
1'
b1101011 7
#2240000
0!
0'
#2250000
1!
1'
b1101100 7
#2260000
0!
0'
#2270000
1!
1'
b1101101 7
#2280000
0!
0'
#2290000
1!
1'
b1101110 7
#2300000
0!
0'
#2310000
1!
1'
b1101111 7
#2320000
0!
0'
#2330000
1!
1'
b1110000 7
#2340000
0!
0'
#2350000
1!
1'
b1110001 7
#2360000
0!
0'
#2370000
1!
1'
b1110010 7
#2380000
0!
0'
#2390000
1!
1'
b1110011 7
#2400000
0!
0'
#2410000
1!
1'
b1110100 7
#2420000
0!
0'
#2430000
1!
1'
b1110101 7
#2440000
0!
0'
#2450000
1!
1'
b1110110 7
#2460000
0!
0'
#2470000
1!
1'
b1110111 7
#2480000
0!
0'
#2490000
1!
1'
b1111000 7
#2500000
0!
0'
#2510000
1!
1'
b1111001 7
#2520000
0!
0'
#2530000
1!
1'
b1111010 7
#2540000
0!
0'
#2550000
1!
1'
b1111011 7
#2560000
0!
0'
#2570000
1!
1'
b1111100 7
#2580000
0!
0'
#2590000
1!
1'
b1111101 7
#2600000
0!
0'
#2610000
1!
1'
b1111110 7
#2620000
0!
0'
#2630000
1!
1'
b1111111 7
#2640000
0!
0'
#2650000
1!
1'
b10000000 7
1;
#2660000
0!
0'
#2670000
1!
1'
05
b10000001 7
0$
#2680000
0!
0'
#2690000
1!
1'
b10000010 7
#2700000
0!
0'
#2710000
1!
1'
b10000011 7
#2720000
0!
0'
#2730000
1!
1'
b10000100 7
#2740000
0!
0'
#2750000
1!
1'
b10000101 7
#2760000
0!
0'
#2770000
1!
1'
b10000110 7
#2780000
0!
0'
#2790000
1!
1'
b10000111 7
#2800000
0!
0'
#2810000
1!
1'
b10001000 7
#2820000
0!
0'
#2830000
1!
1'
b10001001 7
#2840000
0!
0'
#2850000
1!
1'
b10001010 7
#2860000
0!
0'
#2870000
1!
1'
b10001011 7
#2880000
0!
0'
#2890000
1!
1'
b10001100 7
#2900000
0!
0'
#2910000
1!
1'
b10001101 7
#2920000
0!
0'
#2930000
1!
1'
b10001110 7
#2940000
0!
0'
#2950000
1!
1'
b10001111 7
#2960000
0!
0'
#2970000
1!
1'
b10010000 7
#2980000
0!
0'
#2990000
1!
1'
b10010001 7
#3000000
0!
0'
#3010000
1!
1'
b10010010 7
#3020000
0!
0'
#3030000
1!
1'
b10010011 7
#3040000
0!
0'
#3050000
1!
1'
b10010100 7
#3060000
0!
0'
#3070000
1!
1'
b10010101 7
#3080000
0!
0'
#3090000
1!
1'
b10010110 7
#3100000
0!
0'
#3110000
1!
1'
b10010111 7
#3120000
0!
0'
#3130000
1!
1'
b10011000 7
#3140000
0!
0'
#3150000
1!
1'
b10011001 7
#3160000
0!
0'
#3170000
1!
1'
b10011010 7
#3180000
0!
0'
#3190000
1!
1'
b10011011 7
#3200000
0!
0'
#3210000
1!
1'
b10011100 7
#3220000
0!
0'
#3230000
1!
1'
b10011101 7
#3240000
0!
0'
#3250000
1!
1'
b10011110 7
#3260000
0!
0'
#3270000
1!
1'
b10011111 7
#3280000
0!
0'
#3290000
1!
1'
b10100000 7
#3300000
0!
0'
#3310000
1!
1'
b10100001 7
#3320000
0!
0'
#3330000
1!
1'
b10100010 7
#3340000
0!
0'
#3350000
1!
1'
b10100011 7
#3360000
0!
0'
#3370000
1!
1'
b10100100 7
#3380000
0!
0'
#3390000
1!
1'
b10100101 7
#3400000
0!
0'
#3410000
1!
1'
b10100110 7
#3420000
0!
0'
#3430000
1!
1'
b10100111 7
#3440000
0!
0'
#3450000
1!
1'
b10101000 7
#3460000
0!
0'
#3470000
1!
1'
b10101001 7
#3480000
0!
0'
#3490000
1!
1'
b10101010 7
#3500000
0!
0'
#3510000
1!
1'
b10101011 7
#3520000
0!
0'
#3530000
1!
1'
b10101100 7
18
#3540000
0!
0'
#3550000
1!
1'
16
b10101101 7
1%
#3560000
0!
0'
#3570000
1!
1'
b10101110 7
#3580000
0!
0'
#3590000
1!
1'
b10101111 7
#3600000
0!
0'
#3610000
1!
1'
b10110000 7
#3620000
0!
0'
#3630000
1!
1'
b10110001 7
#3640000
0!
0'
#3650000
1!
1'
b10110010 7
#3660000
0!
0'
#3670000
1!
1'
b10110011 7
#3680000
0!
0'
#3690000
1!
1'
b10110100 7
#3700000
0!
0'
#3710000
1!
1'
b10110101 7
#3720000
0!
0'
#3730000
1!
1'
b10110110 7
#3740000
0!
0'
#3750000
1!
1'
b10110111 7
#3760000
0!
0'
#3770000
1!
1'
b10111000 7
#3780000
0!
0'
#3790000
1!
1'
b10111001 7
#3800000
0!
0'
#3810000
1!
1'
b10111010 7
#3820000
0!
0'
#3830000
1!
1'
b10111011 7
#3840000
0!
0'
#3850000
1!
1'
b10111100 7
#3860000
0!
0'
#3870000
1!
1'
b10111101 7
#3880000
0!
0'
#3890000
1!
1'
b10111110 7
#3900000
0!
0'
#3910000
1!
1'
b10111111 7
#3920000
0!
0'
#3930000
1!
1'
b11000000 7
#3940000
0!
0'
#3950000
1!
1'
b11000001 7
#3960000
0!
0'
#3970000
1!
1'
b11000010 7
#3980000
0!
0'
#3990000
1!
1'
b11000011 7
#4000000
0!
0'
#4010000
1!
1'
b11000100 7
#4020000
0!
0'
#4030000
1!
1'
b11000101 7
#4040000
0!
0'
#4050000
1!
1'
b11000110 7
#4060000
0!
0'
#4070000
1!
1'
b11000111 7
#4080000
0!
0'
#4090000
1!
1'
b11001000 7
#4100000
0!
0'
#4110000
1!
1'
b11001001 7
#4120000
0!
0'
#4130000
1!
1'
b11001010 7
#4140000
0!
0'
#4150000
1!
1'
b11001011 7
#4160000
0!
0'
#4170000
1!
1'
b11001100 7
#4180000
0!
0'
#4190000
1!
1'
b11001101 7
#4200000
0!
0'
#4210000
1!
1'
b11001110 7
#4220000
0!
0'
#4230000
1!
1'
b11001111 7
#4240000
0!
0'
#4250000
1!
1'
b11010000 7
#4260000
0!
0'
#4270000
1!
1'
b11010001 7
#4280000
0!
0'
#4290000
1!
1'
b11010010 7
#4300000
0!
0'
#4310000
1!
1'
b11010011 7
#4320000
0!
0'
#4330000
1!
1'
b11010100 7
#4340000
0!
0'
#4350000
1!
1'
b11010101 7
#4360000
0!
0'
#4370000
1!
1'
b11010110 7
#4380000
0!
0'
#4390000
1!
1'
b11010111 7
#4400000
0!
0'
#4410000
1!
1'
b11011000 7
#4420000
0!
0'
#4430000
1!
1'
b11011001 7
#4440000
0!
0'
#4450000
1!
1'
b11011010 7
#4460000
0!
0'
#4470000
1!
1'
b11011011 7
#4480000
0!
0'
#4490000
1!
1'
b11011100 7
#4500000
0!
0'
#4510000
1!
1'
b11011101 7
#4520000
0!
0'
#4530000
1!
1'
b11011110 7
#4540000
0!
0'
#4550000
1!
1'
b11011111 7
#4560000
0!
0'
#4570000
1!
1'
b11100000 7
#4580000
0!
0'
#4590000
1!
1'
b11100001 7
#4600000
0!
0'
#4610000
1!
1'
b11100010 7
#4620000
0!
0'
#4630000
1!
1'
b11100011 7
#4640000
0!
0'
#4650000
1!
1'
b11100100 7
#4660000
0!
0'
#4670000
1!
1'
b11100101 7
#4680000
0!
0'
#4690000
1!
1'
b11100110 7
#4700000
0!
0'
#4710000
1!
1'
b11100111 7
#4720000
0!
0'
#4730000
1!
1'
b11101000 7
#4740000
0!
0'
#4750000
1!
1'
b11101001 7
#4760000
0!
0'
#4770000
1!
1'
b11101010 7
#4780000
0!
0'
#4790000
1!
1'
b11101011 7
#4800000
0!
0'
#4810000
1!
1'
b11101100 7
#4820000
0!
0'
#4830000
1!
1'
b11101101 7
#4840000
0!
0'
#4850000
1!
1'
b11101110 7
#4860000
0!
0'
#4870000
1!
1'
b11101111 7
#4880000
0!
0'
#4890000
1!
1'
b11110000 7
#4900000
0!
0'
#4910000
1!
1'
b11110001 7
#4920000
0!
0'
#4930000
1!
1'
b11110010 7
#4940000
0!
0'
#4950000
1!
1'
b11110011 7
#4960000
0!
0'
#4970000
1!
1'
b11110100 7
#4980000
0!
0'
#4990000
1!
1'
b11110101 7
#5000000
0!
0'
#5010000
1!
1'
b11110110 7
#5020000
0!
0'
#5030000
1!
1'
b11110111 7
#5040000
0!
0'
#5050000
1!
1'
b11111000 7
#5060000
0!
0'
#5070000
1!
1'
b11111001 7
#5080000
0!
0'
#5090000
1!
1'
b11111010 7
#5100000
0!
0'
#5110000
1!
1'
b11111011 7
#5120000
0!
0'
#5130000
1!
1'
b11111100 7
#5140000
0!
0'
#5150000
1!
1'
b11111101 7
#5160000
0!
0'
#5170000
1!
1'
b11111110 7
#5180000
0!
0'
#5190000
1!
1'
b11111111 7
#5200000
0!
0'
#5210000
1!
1'
b100000000 7
#5220000
0!
0'
#5230000
1!
1'
b100000001 7
#5240000
0!
0'
#5250000
1!
1'
b100000010 7
#5260000
0!
0'
#5270000
1!
1'
b100000011 7
#5280000
0!
0'
#5290000
1!
1'
b100000100 7
#5300000
0!
0'
#5310000
1!
1'
b100000101 7
#5320000
0!
0'
#5330000
1!
1'
b100000110 7
#5340000
0!
0'
#5350000
1!
1'
b100000111 7
#5360000
0!
0'
#5370000
1!
1'
b100001000 7
#5380000
0!
0'
#5390000
1!
1'
b100001001 7
#5400000
0!
0'
#5410000
1!
1'
b100001010 7
#5420000
0!
0'
#5430000
1!
1'
b100001011 7
#5440000
0!
0'
#5450000
1!
1'
b100001100 7
#5460000
0!
0'
#5470000
1!
1'
b100001101 7
#5480000
0!
0'
#5490000
1!
1'
b100001110 7
#5500000
0!
0'
#5510000
1!
1'
b100001111 7
#5520000
0!
0'
#5530000
1!
1'
b100010000 7
#5540000
0!
0'
#5550000
1!
1'
b100010001 7
#5560000
0!
0'
#5570000
1!
1'
b100010010 7
#5580000
0!
0'
#5590000
1!
1'
b100010011 7
#5600000
0!
0'
#5610000
1!
1'
b100010100 7
#5620000
0!
0'
#5630000
1!
1'
b100010101 7
#5640000
0!
0'
#5650000
1!
1'
b100010110 7
#5660000
0!
0'
#5670000
1!
1'
b100010111 7
#5680000
0!
0'
#5690000
1!
1'
b100011000 7
#5700000
0!
0'
#5710000
1!
1'
b100011001 7
#5720000
0!
0'
#5730000
1!
1'
b100011010 7
#5740000
0!
0'
#5750000
1!
1'
b100011011 7
#5760000
0!
0'
#5770000
1!
1'
b100011100 7
#5780000
0!
0'
#5790000
1!
1'
b100011101 7
#5800000
0!
0'
#5810000
1!
1'
b100011110 7
#5820000
0!
0'
#5830000
1!
1'
b100011111 7
#5840000
0!
0'
#5850000
1!
1'
b100100000 7
#5860000
0!
0'
#5870000
1!
1'
b100100001 7
#5880000
0!
0'
#5890000
1!
1'
b100100010 7
#5900000
0!
0'
#5910000
1!
1'
b100100011 7
#5920000
0!
0'
#5930000
1!
1'
b100100100 7
#5940000
0!
0'
#5950000
1!
1'
b100100101 7
#5960000
0!
0'
#5970000
1!
1'
b100100110 7
#5980000
0!
0'
#5990000
1!
1'
b100100111 7
#6000000
0!
0'
#6010000
1!
1'
b100101000 7
#6020000
0!
0'
#6030000
1!
1'
b100101001 7
#6040000
0!
0'
#6050000
1!
1'
b100101010 7
#6060000
0!
0'
#6070000
1!
1'
b100101011 7
#6080000
0!
0'
#6090000
1!
1'
b100101100 7
#6100000
0!
0'
#6110000
1!
1'
b100101101 7
#6120000
0!
0'
#6130000
1!
1'
b100101110 7
#6140000
0!
0'
#6150000
1!
1'
b100101111 7
#6160000
0!
0'
#6170000
1!
1'
b100110000 7
#6180000
0!
0'
#6190000
1!
1'
b100110001 7
#6200000
0!
0'
#6210000
1!
1'
b100110010 7
#6220000
0!
0'
#6230000
1!
1'
b100110011 7
#6240000
0!
0'
#6250000
1!
1'
b100110100 7
#6260000
0!
0'
#6270000
1!
1'
b100110101 7
#6280000
0!
0'
#6290000
1!
1'
b100110110 7
#6300000
0!
0'
#6310000
1!
1'
b100110111 7
#6320000
0!
0'
#6330000
1!
1'
b100111000 7
#6340000
0!
0'
#6350000
1!
1'
b100111001 7
#6360000
0!
0'
#6370000
1!
1'
b100111010 7
#6380000
0!
0'
#6390000
1!
1'
b100111011 7
#6400000
0!
0'
#6410000
1!
1'
b100111100 7
#6420000
0!
0'
#6430000
1!
1'
b100111101 7
#6440000
0!
0'
#6450000
1!
1'
b100111110 7
#6460000
0!
0'
#6470000
1!
1'
b100111111 7
#6480000
0!
0'
#6490000
1!
1'
b101000000 7
#6500000
0!
0'
#6510000
1!
1'
b101000001 7
#6520000
0!
0'
#6530000
1!
1'
b101000010 7
#6540000
0!
0'
#6550000
1!
1'
b101000011 7
#6560000
0!
0'
#6570000
1!
1'
b101000100 7
#6580000
0!
0'
#6590000
1!
1'
b101000101 7
#6600000
0!
0'
#6610000
1!
1'
b101000110 7
#6620000
0!
0'
#6630000
1!
1'
b101000111 7
#6640000
0!
0'
#6650000
1!
1'
b101001000 7
#6660000
0!
0'
#6670000
1!
1'
b101001001 7
#6680000
0!
0'
#6690000
1!
1'
b101001010 7
#6700000
0!
0'
#6710000
1!
1'
b101001011 7
#6720000
0!
0'
#6730000
1!
1'
b101001100 7
#6740000
0!
0'
#6750000
1!
1'
b101001101 7
#6760000
0!
0'
#6770000
1!
1'
b101001110 7
#6780000
0!
0'
#6790000
1!
1'
b101001111 7
#6800000
0!
0'
#6810000
1!
1'
b101010000 7
#6820000
0!
0'
#6830000
1!
1'
b101010001 7
#6840000
0!
0'
#6850000
1!
1'
b101010010 7
#6860000
0!
0'
#6870000
1!
1'
b101010011 7
#6880000
0!
0'
#6890000
1!
1'
b101010100 7
#6900000
0!
0'
#6910000
1!
1'
b101010101 7
#6920000
0!
0'
#6930000
1!
1'
b101010110 7
#6940000
0!
0'
#6950000
1!
1'
b101010111 7
#6960000
0!
0'
#6970000
1!
1'
b101011000 7
#6980000
0!
0'
#6990000
1!
1'
b101011001 7
#7000000
0!
0'
#7010000
1!
1'
b101011010 7
#7020000
0!
0'
#7030000
1!
1'
b101011011 7
#7040000
0!
0'
#7050000
1!
1'
b101011100 7
#7060000
0!
0'
#7070000
1!
1'
b101011101 7
#7080000
0!
0'
#7090000
1!
1'
b101011110 7
#7100000
0!
0'
#7110000
1!
1'
b101011111 7
#7120000
0!
0'
#7130000
1!
1'
b101100000 7
#7140000
0!
0'
#7150000
1!
1'
b101100001 7
#7160000
0!
0'
#7170000
1!
1'
b101100010 7
#7180000
0!
0'
#7190000
1!
1'
b101100011 7
#7200000
0!
0'
#7210000
1!
1'
b101100100 7
#7220000
0!
0'
#7230000
1!
1'
b101100101 7
#7240000
0!
0'
#7250000
1!
1'
b101100110 7
#7260000
0!
0'
#7270000
1!
1'
b101100111 7
#7280000
0!
0'
#7290000
1!
1'
b101101000 7
#7300000
0!
0'
#7310000
1!
1'
b101101001 7
#7320000
0!
0'
#7330000
1!
1'
b101101010 7
#7340000
0!
0'
#7350000
1!
1'
b101101011 7
#7360000
0!
0'
#7370000
1!
1'
b101101100 7
#7380000
0!
0'
#7390000
1!
1'
b101101101 7
#7400000
0!
0'
#7410000
1!
1'
b101101110 7
#7420000
0!
0'
#7430000
1!
1'
b101101111 7
#7440000
0!
0'
#7450000
1!
1'
b101110000 7
#7460000
0!
0'
#7470000
1!
1'
b101110001 7
#7480000
0!
0'
#7490000
1!
1'
b101110010 7
#7500000
0!
0'
#7510000
1!
1'
b101110011 7
#7520000
0!
0'
#7530000
1!
1'
b101110100 7
#7540000
0!
0'
#7550000
1!
1'
b101110101 7
#7560000
0!
0'
#7570000
1!
1'
b101110110 7
#7580000
0!
0'
#7590000
1!
1'
b101110111 7
#7600000
0!
0'
#7610000
1!
1'
b101111000 7
#7620000
0!
0'
#7630000
1!
1'
b101111001 7
#7640000
0!
0'
#7650000
1!
1'
b101111010 7
#7660000
0!
0'
#7670000
1!
1'
b101111011 7
#7680000
0!
0'
#7690000
1!
1'
b101111100 7
#7700000
0!
0'
#7710000
1!
1'
b101111101 7
#7720000
0!
0'
#7730000
1!
1'
b101111110 7
#7740000
0!
0'
#7750000
1!
1'
b101111111 7
#7760000
0!
0'
#7770000
1!
1'
b110000000 7
#7780000
0!
0'
#7790000
1!
1'
b110000001 7
#7800000
0!
0'
#7810000
1!
1'
b110000010 7
#7820000
0!
0'
#7830000
1!
1'
b110000011 7
#7840000
0!
0'
#7850000
1!
1'
b110000100 7
#7860000
0!
0'
#7870000
1!
1'
b110000101 7
#7880000
0!
0'
#7890000
1!
1'
b110000110 7
#7900000
0!
0'
#7910000
1!
1'
b110000111 7
#7920000
0!
0'
#7930000
1!
1'
b110001000 7
#7940000
0!
0'
#7950000
1!
1'
b110001001 7
#7960000
0!
0'
#7970000
1!
1'
b110001010 7
#7980000
0!
0'
#7990000
1!
1'
b110001011 7
#8000000
0!
0'
#8010000
1!
1'
b110001100 7
#8020000
0!
0'
#8030000
1!
1'
b110001101 7
#8040000
0!
0'
#8050000
1!
1'
b110001110 7
#8060000
0!
0'
#8070000
1!
1'
b110001111 7
#8080000
0!
0'
#8090000
1!
1'
b110010000 7
#8100000
0!
0'
#8110000
1!
1'
b110010001 7
#8120000
0!
0'
#8130000
1!
1'
b110010010 7
#8140000
0!
0'
#8150000
1!
1'
b110010011 7
#8160000
0!
0'
#8170000
1!
1'
b110010100 7
#8180000
0!
0'
#8190000
1!
1'
b110010101 7
#8200000
0!
0'
#8210000
1!
1'
b110010110 7
#8220000
0!
0'
#8230000
1!
1'
b110010111 7
#8240000
0!
0'
#8250000
1!
1'
b110011000 7
#8260000
0!
0'
#8270000
1!
1'
b110011001 7
#8280000
0!
0'
#8290000
1!
1'
b110011010 7
#8300000
0!
0'
#8310000
1!
1'
b110011011 7
#8320000
0!
0'
#8330000
1!
1'
b110011100 7
#8340000
0!
0'
#8350000
1!
1'
b110011101 7
#8360000
0!
0'
#8370000
1!
1'
b110011110 7
#8380000
0!
0'
#8390000
1!
1'
b110011111 7
#8400000
0!
0'
#8410000
1!
1'
b110100000 7
#8420000
0!
0'
#8430000
1!
1'
b110100001 7
#8440000
0!
0'
#8450000
1!
1'
b110100010 7
#8460000
0!
0'
#8470000
1!
1'
b110100011 7
#8480000
0!
0'
#8490000
1!
1'
b110100100 7
#8500000
0!
0'
#8510000
1!
1'
b110100101 7
#8520000
0!
0'
#8530000
1!
1'
b110100110 7
#8540000
0!
0'
#8550000
1!
1'
b110100111 7
#8560000
0!
0'
#8570000
1!
1'
b110101000 7
#8580000
0!
0'
#8590000
1!
1'
b110101001 7
#8600000
0!
0'
#8610000
1!
1'
b110101010 7
#8620000
0!
0'
#8630000
1!
1'
b110101011 7
#8640000
0!
0'
#8650000
1!
1'
b110101100 7
#8660000
0!
0'
#8670000
1!
1'
b110101101 7
#8680000
0!
0'
#8690000
1!
1'
b110101110 7
#8700000
0!
0'
#8710000
1!
1'
b110101111 7
#8720000
0!
0'
#8730000
1!
1'
b110110000 7
#8740000
0!
0'
#8750000
1!
1'
b110110001 7
#8760000
0!
0'
#8770000
1!
1'
b110110010 7
#8780000
0!
0'
#8790000
1!
1'
b110110011 7
#8800000
0!
0'
#8810000
1!
1'
b110110100 7
#8820000
0!
0'
#8830000
1!
1'
b110110101 7
#8840000
0!
0'
#8850000
1!
1'
b110110110 7
#8860000
0!
0'
#8870000
1!
1'
b110110111 7
#8880000
0!
0'
#8890000
1!
1'
b110111000 7
#8900000
0!
0'
#8910000
1!
1'
b110111001 7
#8920000
0!
0'
#8930000
1!
1'
b110111010 7
#8940000
0!
0'
#8950000
1!
1'
b110111011 7
#8960000
0!
0'
#8970000
1!
1'
b110111100 7
#8980000
0!
0'
#8990000
1!
1'
b110111101 7
#9000000
0!
0'
#9010000
1!
1'
b110111110 7
#9020000
0!
0'
#9030000
1!
1'
b110111111 7
#9040000
0!
0'
#9050000
1!
1'
b111000000 7
#9060000
0!
0'
#9070000
1!
1'
b111000001 7
#9080000
0!
0'
#9090000
1!
1'
b111000010 7
#9100000
0!
0'
#9110000
1!
1'
b111000011 7
#9120000
0!
0'
#9130000
1!
1'
b111000100 7
#9140000
0!
0'
#9150000
1!
1'
b111000101 7
#9160000
0!
0'
#9170000
1!
1'
b111000110 7
#9180000
0!
0'
#9190000
1!
1'
b111000111 7
#9200000
0!
0'
#9210000
1!
1'
b111001000 7
#9220000
0!
0'
#9230000
1!
1'
b111001001 7
#9240000
0!
0'
#9250000
1!
1'
b111001010 7
#9260000
0!
0'
#9270000
1!
1'
b111001011 7
